cbltooling/__init__.py
cbltooling-0.0.1.dist-info/METADATA
cbltooling-0.0.1.dist-info/WHEEL
cbltooling-0.0.1.dist-info/licenses/LICENSE
cbltooling-0.0.1.dist-info/RECORD
