Metadata-Version: 2.4
Name: cbltooling
Version: 0.0.1
Summary: Python tooling for the Computational Biomechanics Lab at TU Delft
Project-URL: Homepage, https://github.com/ComputationalBiomechanicsLab/cbltooling
Project-URL: Documentation, https://computationalbiomechanicslab.github.io/cbltooling
Author-email: Adam Kewley <a.kewley@tudelft.nl>
License-Expression: Apache-2.0
License-File: LICENSE
Classifier: Development Status :: 2 - Pre-Alpha
Classifier: Intended Audience :: Science/Research
Classifier: License :: OSI Approved :: Apache Software License
Classifier: Operating System :: OS Independent
Classifier: Programming Language :: Python :: 3
Requires-Dist: numpy
